augment/__init__.py
augment/effects.py
waveaugment-0.2.4.dist-info/LICENSE
waveaugment-0.2.4.dist-info/METADATA
waveaugment-0.2.4.dist-info/WHEEL
waveaugment-0.2.4.dist-info/top_level.txt
waveaugment-0.2.4.dist-info/RECORD
