Metadata-Version: 2.1
Name: waveaugment
Version: 0.2.4
Summary: WaveAugment performs data augmentation on audio data. 
Home-page: https://github.com/facebookresearch/WavAugment
License: UNKNOWN
Platform: UNKNOWN
License-File: LICENSE
Requires-Dist: torch (>=1.7.1)
Requires-Dist: torchaudio
